sqlgrain/__init__.py
sqlgrain/data_source.py
sqlgrain/records.py
sqlgrain/util.py
sql_grain-0.2.3.dist-info/METADATA
sql_grain-0.2.3.dist-info/WHEEL
sql_grain-0.2.3.dist-info/top_level.txt
sql_grain-0.2.3.dist-info/RECORD
