Metadata-Version: 2.4
Name: sql-grain
Version: 0.2.3
Summary: Sqlite databases as Grain datasets.
Requires-Python: >=3.11
Requires-Dist: grain>=0.2.15
Requires-Dist: msgpack>=1.1.2
